.DS_Store
data/__init__.py
enricher/__init__.py
enricher/enrich.py
enricher/data/PathwayCommons9.All.hgnc.sif.gz
enricher/data/secondary_intx_regulon.pkl
enricher/features/__init__.py
enricher/features/expression_utils.py
enricher/plot/__init__.py
enricher/plot/plot_utils.py
enricher/regulon/__init__.py
enricher/regulon/regulon_enrichment.py
enricher/regulon/regulon_utils.py
regulon_enrichment-0.7a2.data/data/enricher/PathwayCommons9.All.hgnc.sif.gz
regulon_enrichment-0.7a2.data/data/enricher/secondary_intx_regulon.pkl
regulon_enrichment-0.7a2.dist-info/LICENSE
regulon_enrichment-0.7a2.dist-info/METADATA
regulon_enrichment-0.7a2.dist-info/WHEEL
regulon_enrichment-0.7a2.dist-info/entry_points.txt
regulon_enrichment-0.7a2.dist-info/top_level.txt
regulon_enrichment-0.7a2.dist-info/RECORD
