Metadata-Version: 2.1
Name: regulon-enrichment
Version: 0.7a2
Summary: This package leverages pathway information and gene expression data to produce
Home-page: https://github.com/JEstabrook/regulon-enrichment
Author: Joseph Estabrook
Author-email: estabroj@ohsu.edu
License: UNKNOWN
Platform: UNKNOWN
Classifier: Programming Language :: Python :: 3
Classifier: License :: OSI Approved :: MIT License
Classifier: Operating System :: OS Independent
Requires-Python: ==3.6.13
Requires-Dist: numpy (==1.17.3)
Requires-Dist: pandas (==0.25.3)
Requires-Dist: scikit-learn (==0.21.3)
Requires-Dist: scipy (==1.5.2)
Requires-Dist: tqdm (==4.38.0)
Requires-Dist: dill (==0.3.1.1)
